Metadata-Version: 1.0
Name: dist-kanishka
Version: 0.3
Summary: Gaussian and Binomial distributions
Home-page: UNKNOWN
Author: Kanishka Dandeniya
Author-email: kanishka.d@eng.pdn.ac.lk
License: LICENSE
Platform: UNKNOWN
